modular_message_bot/__init__.py
modular_message_bot/factory.py
modular_message_bot/job_runner.py
modular_message_bot/job_validator.py
modular_message_bot/run.py
modular_message_bot/run_all.py
modular_message_bot/run_by_id.py
modular_message_bot/run_details_loader.py
modular_message_bot/run_validate_all.py
modular_message_bot/string_interpolator.py
modular_message_bot/config/__init__.py
modular_message_bot/config/config_collection.py
modular_message_bot/config/config_interpolator.py
modular_message_bot/config/constants.py
modular_message_bot/config/default_config_provider.py
modular_message_bot/config/env_config_provider.py
modular_message_bot/config/secret_files_config_provider.py
modular_message_bot/handlers/__init__.py
modular_message_bot/handlers/abstract_handler.py
modular_message_bot/handlers/handler_collections.py
modular_message_bot/handlers/inputs/__init__.py
modular_message_bot/handlers/inputs/abstract_input_handler.py
modular_message_bot/handlers/inputs/date_time_input.py
modular_message_bot/handlers/inputs/elastic_search_input.py
modular_message_bot/handlers/inputs/github_prs_input.py
modular_message_bot/handlers/inputs/gitlab_merge_requests_input.py
modular_message_bot/handlers/inputs/open_weather_city_input.py
modular_message_bot/handlers/inputs/random_message_input.py
modular_message_bot/handlers/outputs/__init__.py
modular_message_bot/handlers/outputs/abstract_output_hander.py
modular_message_bot/handlers/outputs/easy_http_output.py
modular_message_bot/handlers/outputs/pushover_output.py
modular_message_bot/handlers/outputs/slack_output.py
modular_message_bot/handlers/outputs/stdout_output.py
modular_message_bot/handlers/pres/__init__.py
modular_message_bot/handlers/pres/abstract_pre_handler.py
modular_message_bot/handlers/pres/chance_pre.py
modular_message_bot/handlers/processors/__init__.py
modular_message_bot/handlers/processors/abstract_processor_handler.py
modular_message_bot/handlers/processors/abstract_regex_match_handler.py
modular_message_bot-2.5.0.dist-info/LICENSE
modular_message_bot-2.5.0.dist-info/METADATA
modular_message_bot-2.5.0.dist-info/WHEEL
modular_message_bot-2.5.0.dist-info/top_level.txt
modular_message_bot-2.5.0.dist-info/RECORD
