Metadata-Version: 2.1
Name: modular-message-bot
Version: 2.5.0
Summary: Takes data from sources and sends them somewhere based on a schedule that is defined in YAML
Home-page: https://gitlab.com/mage-sauce/programs/modular-message-bot
Author: Jeremy Sells
Author-email: mrjeremysells@gmail.com
License: UNKNOWN
Platform: any
Classifier: License :: OSI Approved :: MIT License
Classifier: Operating System :: OS Independent
Classifier: Programming Language :: Python
Classifier: Programming Language :: Python :: 3.8
Classifier: Programming Language :: Python :: 3 :: Only
Requires-Python: >=3.8.0
Requires-Dist: APScheduler (>=3.6.3)
Requires-Dist: elasticsearch (>=7.10.1)
Requires-Dist: pyjq (>=2.5.1)
Requires-Dist: python-dotenv (>=0.13.0)
Requires-Dist: pyyaml (>=5.4.1)
Requires-Dist: requests (>=2.23.0)
Provides-Extra: dev
Requires-Dist: black (==19.10b0) ; extra == 'dev'
Requires-Dist: coverage (==5.3.1) ; extra == 'dev'
Requires-Dist: flake8 (==3.8.4) ; extra == 'dev'
Requires-Dist: isort (==5.7.0) ; extra == 'dev'
Requires-Dist: mypy (==0.800) ; extra == 'dev'
Requires-Dist: pdoc (==1.1.0) ; extra == 'dev'
Requires-Dist: pip-tools (==5.5.0) ; extra == 'dev'
Requires-Dist: pygount (==1.2.4) ; extra == 'dev'
Requires-Dist: pytest-mock (==3.5.1) ; extra == 'dev'
Requires-Dist: pytest (==6.2.1) ; extra == 'dev'
Requires-Dist: twine (==3.3.0) ; extra == 'dev'
